setup.py
Yelpy.egg-info/PKG-INFO
Yelpy.egg-info/SOURCES.txt
Yelpy.egg-info/dependency_links.txt
Yelpy.egg-info/requires.txt
Yelpy.egg-info/top_level.txt
yelpy/__init__.py
yelpy/business_query.py
yelpy/search_bounds.py
yelpy/search_location.py
yelpy/search_query.py
yelpy/yelpy_client.py
yelpy/yelpy_objects.py
yelpy/yelpy_signer.py