Metadata-Version: 1.0
Name: Yelpy
Version: 0.2.6dev
Summary: Yelp API Client
Home-page: http://www.bryanmarty.com
Author: Bryan Marty
Author-email: hello@bryanmarty.com
License: GPLv2
Platform: UNKNOWN
